ensfc_stemm/__init__.py
ensfc_stemm/calculations.py
ensfc_stemm/equations.py
ensfc_stemm/models.py
tests/__init__.py
tests/test_calculations.py
tests/test_equations.py
tests/test_models.py
ensfc_stemm-0.1.5.dist-info/LICENSE
ensfc_stemm-0.1.5.dist-info/METADATA
ensfc_stemm-0.1.5.dist-info/WHEEL
ensfc_stemm-0.1.5.dist-info/top_level.txt
ensfc_stemm-0.1.5.dist-info/RECORD
