Metadata-Version: 2.1
Name: ensfc-stemm
Version: 0.1.5
License-File: LICENSE
Requires-Dist: sympy
